pyinsane2/__init__.py
pyinsane2/_version.py
pyinsane2/util.py
pyinsane2/sane/__init__.py
pyinsane2/sane/abstract.py
pyinsane2/sane/abstract_proc.py
pyinsane2/sane/daemon.py
pyinsane2/sane/rawapi.py
pyinsane2/wia/__init__.py
pyinsane2/wia/_rawapi.pyd
pyinsane2/wia/abstract.py
pyinsane2/wia/rawapi.py
pyinsane2-2.0.13.dist-info/DESCRIPTION.rst
pyinsane2-2.0.13.dist-info/METADATA
pyinsane2-2.0.13.dist-info/RECORD
pyinsane2-2.0.13.dist-info/WHEEL
pyinsane2-2.0.13.dist-info/metadata.json
pyinsane2-2.0.13.dist-info/top_level.txt
