Metadata-Version: 2.0
Name: pyinsane2
Version: 2.0.13
Summary: Python library to access and use image scanners (Linux/Windows/etc)
Home-page: https://github.com/openpaperwork/pyinsane
Author: Jerome Flesch
Author-email: jflesch@openpaper.work
License: GPLv3+
Download-URL: https://github.com/openpaperwork/pyinsane/archive/2.0.13.zip
Keywords: sane scanner
Platform: UNKNOWN
Classifier: Development Status :: 5 - Production/Stable
Classifier: Intended Audience :: Developers
Classifier: License :: OSI Approved :: GNU General Public License v3 or later (GPLv3+)
Classifier: Operating System :: POSIX :: Linux
Classifier: Programming Language :: Python
Classifier: Programming Language :: Python :: 2
Classifier: Programming Language :: Python :: 2.7
Classifier: Programming Language :: Python :: 3
Classifier: Programming Language :: Python :: 3.3
Classifier: Programming Language :: Python :: 3.4
Classifier: Programming Language :: Python :: 3.5
Classifier: Topic :: Multimedia :: Graphics :: Capture :: Scanners
Classifier: Topic :: Software Development :: Libraries :: Python Modules
Requires-Dist: Pillow
